{
    "url": "https://cuevana.pizza/pelicula/destino-final",
    "title": "Destino final",
    "duration": "1h 38m",
    "year": "2000",
    "genres": [
        "Terror"
    ],
    "actors": [
        "Devon Sawa",
        "Ali Larter",
        "Kerr Smith",
        "Kristen Cloke",
        "Seann William Scott",
        "Chad Donella",
        "Amanda Detmer",
        "Tony Todd",
        "Daniel Roebuck",
        "Roger Guenveur Smith",
        "Brendan Fehr",
        "Forbes Angus",
        "Lisa Marie Caruk",
        "Christine Chatelain",
        "Robert Wisden",
        "Barbara Tyson",
        "Fred Keating",
        "P. Lynn Johnson",
        "Larry Gilman",
        "Guy Fauchon"
    ],
    "description": "Al subir a un avión con destino a Paris, junto con sus compañeros de clase, Alex tiene una premonición, por lo que desembarca justo antes de despegar junto a seis de sus amigos y una profesora. Poco después el aparato explota en el aire. El grupo de supervivientes se verá perseguido por la dama de la guadaña, la propia muerte, que no se dará por vencida. Acosado por el FBI que considera a Alex responsable del accidente y perseguido por sus propios miedos, el joven deberá descubrir que las coincidencias y los accidentes no son algo casual.",
    "cover": "https://cuevana.pizza/resize/###/storage/41136/R83Qit4oaadnTEPECkMLkyr1vRYZNMgLP3sIuCqN.jpg",
    "players": [
        {
            "type": "lat",
            "urls": [
                "https://akamai.interplanetary.video/?v=aHR0cHM6Ly9ha2FtYWktY2RuLWNvbnRlbnQuaW50ZXJwbGFuZXRhcnkudmlkZW8vZW1iZWQtOTZnbHRuNHc1cmIyLmh0bWw=",
                "https://akamai.interplanetary.video/?v=aHR0cHM6Ly91cWxvYWQuY29tL2VtYmVkLWZxdzlzN2YzbTl4eS5odG1s"
            ]
        },
        {
            "type": "cas",
            "urls": [
                "https://akamai.interplanetary.video/?v=aHR0cHM6Ly9ha2FtYWktY2RuLWNvbnRlbnQuaW50ZXJwbGFuZXRhcnkudmlkZW8vZW1iZWQtOTdidXM1bW51M2p2Lmh0bWw=",
                "https://akamai.interplanetary.video/?v=aHR0cHM6Ly91cWxvYWQuY29tL2VtYmVkLXk3YnU4dmNqZXFoNy5odG1s"
            ]
        },
        {
            "type": "sub",
            "urls": [
                "https://akamai.interplanetary.video/?v=aHR0cHM6Ly9ha2FtYWktY2RuLWNvbnRlbnQuaW50ZXJwbGFuZXRhcnkudmlkZW8vZW1iZWQtaHV0c2FwZXYyZXVtLmh0bWw=",
                "https://akamai.interplanetary.video/?v=aHR0cHM6Ly91cWxvYWQuY29tL2VtYmVkLXg3ZGZkeXYyZTBoYi5odG1s"
            ]
        }
    ],
    "downloads": [
        {
            "url": "https://1fichier.com/?bd5vnfbgvhgi1exls9cx",
            "type": "la"
        },
        {
            "url": "https://1fichier.com/?8dgorcn29660vh5mcu8e",
            "type": "es"
        },
        {
            "url": "https://1fichier.com/?uyqh87csxc44bpbbo82k",
            "type": "en"
        }
    ]
}