{
    "url": "https://cuevana.pizza/pelicula/el-juego-de-las-llaves",
    "title": "El juego de las llaves",
    "duration": "0h 0m",
    "year": "2022",
    "genres": [
        "Comedia"
    ],
    "actors": [
        "Fernando Guallar",
        "Eva Ugarte",
        "Miren Ibarguren",
        "Tamar Novas",
        "Alina Nastase",
        "María Castro",
        "Justina Bustos",
        "Richard Farré",
        "Cintia García"
    ],
    "description": "Laura lleva toda la vida con Antonio y, justo cuando se empieza a plantear si realmente esa es la vida que quiere, Sergio y Siena se cruzan en sus vidas. Sergio es un excompañero de instituto y Siena, su novia millenial que llega para revolucionar las vidas de todos. Laura, Raquel y Cris, íntimas amigas desde hace años, convencen a sus respectivos maridos para jugar a un juego que les propone Siena: el juego de las llaves. El juego consiste en que todos ponen sus llaves en un cuenco. Al azar, cada uno escoge unas llaves y este debe ir a pasar la noche con el dueño o la dueña de las llaves. Ese juego revolucionará al grupo de amigos y sus vidas. Les hará descubrir quiénes son y qué quieren realmente. Una comedia sobre la monogamia a largo plazo, la autorrealización y el placer. Una historia sobre cuatro parejas que son amigos y deciden ser swingers entre ellos. Remake en versión para cine de la serie mexicana del mismo nombre.",
    "cover": "https://cuevana.pizza/resize/###/storage/35064/tC4yQAsyrTQYxm1ex32BZGBSj2Tu0vanykxKn8gc.jpg",
    "players": [
        {
            "type": "cas",
            "urls": [
                "https://akamai.interplanetary.video/?v=aHR0cHM6Ly9ha2FtYWktY2RuLWNvbnRlbnQuaW50ZXJwbGFuZXRhcnkudmlkZW8vZW1iZWQtZHFnaWM2dWVucDNtLmh0bWw=",
                "https://akamai.interplanetary.video/?v=aHR0cHM6Ly91cWxvYWQuY29tL2VtYmVkLTljenMwc2FodWUyai5odG1s"
            ]
        }
    ],
    "downloads": [
        {
            "url": "https://1fichier.com/?xbrmv9n13j51j12sbd3j",
            "type": "es"
        }
    ]
}