{
    "url": "https://cuevana.pizza/pelicula/the-souvenir-part-ii",
    "title": "The Souvenir: Part II",
    "duration": "1h 47m",
    "year": "2021",
    "genres": [
        "Drama"
    ],
    "actors": [
        "Honor Swinton Byrne",
        "Richard Ayoade",
        "Tilda Swinton",
        "Charlie Heaton",
        "Joe Alwyn",
        "Harris Dickinson",
        "Ariane Labed",
        "Jack McMullen",
        "Amber Anderson",
        "Alice McMillan",
        "Tosin Cole",
        "James Spencer Ashworth",
        "Frankie Wilson",
        "Amrou Al-Kadhi",
        "Jaygann Ayeh",
        "Grace Hancock",
        "Gala Botero",
        "Byron Broadbent",
        "Jack W. Gregory",
        "Annabelle Holmes"
    ],
    "description": "Como resultado de una turbulenta relación con un hombre mayor carismático y manipulador, Julia empieza a deshacerse de su amor por él a través de la realización de su película de graduación, separando los hechos de su elaborada ficción. 'The Souvenir Part II' de Joanna Hogg es una historia brillante sobre el primer amor y los años de formación de una mujer joven, un retrato de la artista que trasciende los detalles de la vida cotidiana, una mezcla única y alquímica de memorias y fantasía.",
    "cover": "https://cuevana.pizza/resize/###/storage/22102/aCI00g5w72dv6kbhMsUm6s2qCCcqIueN464bDiVH.jpg",
    "players": [
        {
            "type": "lat",
            "urls": [
                "https://akamai.interplanetary.video/?v=aHR0cHM6Ly9ha2FtYWktY2RuLWNvbnRlbnQuaW50ZXJwbGFuZXRhcnkudmlkZW8vZW1iZWQtOWNhaDZidmZrcTQ5Lmh0bWw=",
                "https://akamai.interplanetary.video/?v=aHR0cHM6Ly91cWxvYWQuY29tL2VtYmVkLW1xdXpvbmNzZDRmcS5odG1s"
            ]
        },
        {
            "type": "sub",
            "urls": [
                "https://akamai.interplanetary.video/?v=aHR0cHM6Ly9ha2FtYWktY2RuLWNvbnRlbnQuaW50ZXJwbGFuZXRhcnkudmlkZW8vZW1iZWQtdWN6bmtoNDlrdm50Lmh0bWw=",
                "https://akamai.interplanetary.video/?v=aHR0cHM6Ly91cWxvYWQuY29tL2VtYmVkLWxza3lrdGhoMmI0by5odG1s"
            ]
        }
    ],
    "downloads": [
        {
            "url": "https://1fichier.com/?ej4x7co7sjx81drnw4z1",
            "type": "la"
        },
        {
            "url": "https://1fichier.com/?agudn2luh68ahcsp95hg",
            "type": "en"
        }
    ]
}