{
    "url": "https://cuevana.pizza/pelicula/hive-colmena",
    "title": "Colmena",
    "duration": "1h 24m",
    "year": "2021",
    "genres": [
        "Drama"
    ],
    "actors": [
        "Yllka Gashi",
        "Çun Lajçi",
        "Aurita Agushi",
        "Kumrije Hoxha",
        "Adriana Matoshi",
        "Molike Maxhuni",
        "Blerta Ismaili",
        "Kaona Sylejmani",
        "Mal Noah Safqiu",
        "Xhejlane Terbunja"
    ],
    "description": "En un pueblo muy unido de Kosovo, las familias luchan para llegar a final de mes, ansiosas por recibir noticias de los maridos, padres e hijos a los que se llevó la guerra. Cuando las abejas de Fahrije dejan de producir miel, decide aprobar el carnet de conducir y se aventura a la ciudad para vender ajvar casero en una tienda de comestibles local. Su ingenuidad y ambición ponen a prueba a los habitantes de un pueblo conservador por naturaleza en el que siguen vigentes las nociones patriarcales y tradicionales de la sociedad. Para poder sobrevivir tiene que superar los insultos y los ataques físicos que tratan de impedir por todos los medios que la mujer pueda valerse por sí misma.",
    "cover": "https://cuevana.pizza/resize/###/storage/12739/W4jlzGzPjMNqeiwrfl6nvZBYsFXeQsFwQQiW440A.jpg",
    "players": [
        {
            "type": "lat",
            "urls": [
                "https://akamai.interplanetary.video/?v=aHR0cHM6Ly9ha2FtYWktY2RuLWNvbnRlbnQuaW50ZXJwbGFuZXRhcnkudmlkZW8vZW1iZWQtM2l5M3ptcW56NWZ5Lmh0bWw=",
                "https://akamai.interplanetary.video/?v=aHR0cHM6Ly91cWxvYWQuY29tL2VtYmVkLXJyNGR6cjliNWF2bS5odG1s"
            ]
        },
        {
            "type": "cas",
            "urls": [
                "https://akamai.interplanetary.video/?v=aHR0cHM6Ly9ha2FtYWktY2RuLWNvbnRlbnQuaW50ZXJwbGFuZXRhcnkudmlkZW8vZW1iZWQtbmg2ZmZ0cG01bmZ1Lmh0bWw=",
                "https://akamai.interplanetary.video/?v=aHR0cHM6Ly91cWxvYWQuY29tL2VtYmVkLXF4aXN2ZHV3Nmhjay5odG1s"
            ]
        },
        {
            "type": "sub",
            "urls": [
                "https://akamai.interplanetary.video/?v=aHR0cHM6Ly9ha2FtYWktY2RuLWNvbnRlbnQuaW50ZXJwbGFuZXRhcnkudmlkZW8vZW1iZWQtejRzNnhnemg2ZHR0Lmh0bWw=",
                "https://akamai.interplanetary.video/?v=aHR0cHM6Ly91cWxvYWQuY29tL2VtYmVkLXBqOTB1YTY0YTMxYy5odG1s"
            ]
        }
    ],
    "downloads": [
        {
            "url": "https://1fichier.com/?9kmfl6lha3s8ob9tzxv8",
            "type": "la"
        },
        {
            "url": "https://1fichier.com/?au9jjfkqj1gceex9i0s0",
            "type": "es"
        },
        {
            "url": "https://1fichier.com/?t6ss1t5dtvmd4znn5ebb",
            "type": "en"
        }
    ]
}