{
    "url": "https://cuevana.pizza/pelicula/the-unlit",
    "title": "The Unlit",
    "duration": "1h 18m",
    "year": "2021",
    "genres": [
        "Suspenso",
        "Terror"
    ],
    "actors": [
        "Cassandra Magrath",
        "John Voce",
        "Nicholas Denton",
        "Francesca Waters",
        "Kevin Hofbauer",
        "Susan Vasilijevic"
    ],
    "description": "Cuando Claire regresa a su ciudad natal, descubre que su antiguo hogar está plagado de terrorífica brujería, y que el pueblo está sumido en el miedo, la decadencia y la locura.",
    "cover": "https://cuevana.pizza/resize/###/storage/10198/bFLyjS2enVxOJX9cKZ5LUOPXrksFx6ziVKaix3kf.jpg",
    "players": [
        {
            "type": "sub",
            "urls": [
                "https://akamai.interplanetary.video/?v=aHR0cHM6Ly9ha2FtYWktY2RuLWNvbnRlbnQuaW50ZXJwbGFuZXRhcnkudmlkZW8vZW1iZWQtNzl0MGh6MmNvbnJtLmh0bWw=",
                "https://akamai.interplanetary.video/?v=aHR0cHM6Ly91cWxvYWQuY29tL2VtYmVkLWM2NTcxMnFwdmlhYy5odG1s"
            ]
        }
    ],
    "downloads": [
        {
            "url": "https://1fichier.com/?epf1t4bls3adkkh35gl4",
            "type": "en"
        }
    ]
}