{
    "url": "https://cuevana.pizza/pelicula/the-wolf-of-snow-hollow",
    "title": "El lobo de Snow Hollow",
    "duration": "1h 23m",
    "year": "2020",
    "genres": [
        "Suspenso",
        "Terror"
    ],
    "actors": [
        "Jim Cummings",
        "Riki Lindhome",
        "Robert Forster",
        "Chloe East",
        "Jimmy Tatro",
        "Marshall Allman",
        "Laura Coover",
        "Jessica Park"
    ],
    "description": "El terror se adueña de un pequeño pueblo al pie de las montañas cuando una serie de cadáveres son descubiertos tras la luna llena. Tras perder a su hija adolescente, incapaz de dormir y al cuidado de su padre enfermo, el oficial Marshall lucha para recordar cada día que no existe tal cosa como eso que llaman \"hombres-lobo\".",
    "cover": "https://cuevana.pizza/resize/###/storage/24639/D2Qhiggsm69ps0C65zzXna9EpH9MoSESrKmqi1Qm.jpg",
    "players": [
        {
            "type": "cas",
            "urls": [
                "https://akamai.interplanetary.video/?v=aHR0cHM6Ly9ha2FtYWktY2RuLWNvbnRlbnQuaW50ZXJwbGFuZXRhcnkudmlkZW8vZW1iZWQteXFlYWp5Z3Y1aWszLmh0bWw=",
                "https://akamai.interplanetary.video/?v=aHR0cHM6Ly91cWxvYWQuY29tL2VtYmVkLTQyamlsc2trYXJhYS5odG1s"
            ]
        },
        {
            "type": "sub",
            "urls": [
                "https://akamai.interplanetary.video/?v=aHR0cHM6Ly9ha2FtYWktY2RuLWNvbnRlbnQuaW50ZXJwbGFuZXRhcnkudmlkZW8vZW1iZWQtZjY2eTdrbWprcWt3Lmh0bWw=",
                "https://akamai.interplanetary.video/?v=aHR0cHM6Ly91cWxvYWQuY29tL2VtYmVkLTR5enZsZmxyMmk5by5odG1s"
            ]
        }
    ],
    "downloads": [
        {
            "url": "https://1fichier.com/?5zk11te4jzr5p2hf05td",
            "type": "es"
        },
        {
            "url": "https://1fichier.com/?wksp66awtgtddnphl8v6",
            "type": "en"
        }
    ]
}