{
    "url": "https://cuevana.pizza/pelicula/the-miseducation-of-cameron-post",
    "title": "La (des)educación de Cameron Post",
    "duration": "1h 32m",
    "year": "2018",
    "genres": [
        "Drama",
        "Romance"
    ],
    "actors": [
        "Chloë Grace Moretz",
        "John Gallagher Jr.",
        "Sasha Lane",
        "Forrest Goodluck",
        "Jennifer Ehle",
        "Marin Ireland",
        "Owen Campbell",
        "Kerry Butler",
        "Quinn Shephard",
        "Emily Skeggs",
        "Melanie Ehrlich",
        "Isaac Jin Solstein",
        "Dalton Harrod",
        "Steven Hauck",
        "McCabe Slye",
        "Dale Soules",
        "Christopher Dylan White",
        "Andre B. Blake",
        "Nick Covell",
        "Cerrone May"
    ],
    "description": "Pennsylvania, 1993. Después de ser sorprendida con otra chica, la adolescente Cameron Post es enviada a un centro de terapia de conversión dirigido por la estricta doctora Lydia Marsh y su hermano, el reverendo Rick, cuyo tratamiento consiste en arrepentirse por sentir «atracción por el mismo sexo». Cameron se hace amiga de sus compañeros Jane y Adam, creando así una nueva familia para enfrentarse a la intolerancia que les rodea.",
    "cover": "https://cuevana.pizza/resize/###/storage/17439/fMB1aBc4rQNkoIUFPHW6uKEs7bqYpFeAqFMzxWXK.jpg",
    "players": [
        {
            "type": "lat",
            "urls": [
                "https://akamai.interplanetary.video/?v=aHR0cHM6Ly9ha2FtYWktY2RuLWNvbnRlbnQuaW50ZXJwbGFuZXRhcnkudmlkZW8vZW1iZWQtYjNsOTR4NGZhYmF6Lmh0bWw=",
                "https://akamai.interplanetary.video/?v=aHR0cHM6Ly91cWxvYWQuY29tL2VtYmVkLXNpOGY5aHd0a3Awcy5odG1s"
            ]
        },
        {
            "type": "cas",
            "urls": [
                "https://akamai.interplanetary.video/?v=aHR0cHM6Ly9ha2FtYWktY2RuLWNvbnRlbnQuaW50ZXJwbGFuZXRhcnkudmlkZW8vZW1iZWQtY28yeGw2M3Rjemk0Lmh0bWw=",
                "https://akamai.interplanetary.video/?v=aHR0cHM6Ly91cWxvYWQuY29tL2VtYmVkLW5qamkyeHdvdGpobC5odG1s"
            ]
        },
        {
            "type": "sub",
            "urls": [
                "https://akamai.interplanetary.video/?v=aHR0cHM6Ly9ha2FtYWktY2RuLWNvbnRlbnQuaW50ZXJwbGFuZXRhcnkudmlkZW8vZW1iZWQtbnY4OXNiZnV3MjlxLmh0bWw=",
                "https://akamai.interplanetary.video/?v=aHR0cHM6Ly91cWxvYWQuY29tL2VtYmVkLW9lczAyaTRncGhhZy5odG1s"
            ]
        }
    ],
    "downloads": []
}