{
    "url": "https://cuevana.pizza/pelicula/amanda",
    "title": "Mi vida con Amanda",
    "duration": "1h 47m",
    "year": "2018",
    "genres": [
        "Drama"
    ],
    "actors": [
        "Vincent Lacoste",
        "Isaure Multrier",
        "Stacy Martin",
        "Ophélia Kolb",
        "Marianne Basler",
        "Jonathan Cohen",
        "Greta Scacchi",
        "Claire Tran",
        "Nabiha Akkari",
        "Bakary Sangaré",
        "Elli Medeiros",
        "Zoé Bruneau",
        "Lily Bensliman",
        "Raphaël Thiéry",
        "Leah Lapiower",
        "Luke Haines",
        "Lawrence Valin",
        "Carole Rochet",
        "Jeanne Candel",
        "Lisa Wisznia"
    ],
    "description": "París, hoy en día. David tiene veinte años y vive el presente. Se gana la vida con pequeños trabajos, y evita tomar decisiones que le comprometan. Es solitario y soñador. Un día se enamora de Lena, una vecina que acaba de llegar. El transcurso tranquilo de su vida estalla de pronto cuando su hermana mayor muere brutalmente en un atentado. David es la única persona que se puede hacer cargo de Amanda, su sobrina de siete años.",
    "cover": "https://cuevana.pizza/resize/###/storage/21853/lDarG1ppIkg0Djqs9xuQ27wAsuaClcNFMltQ7Zf9.jpg",
    "players": [
        {
            "type": "cas",
            "urls": [
                "https://akamai.interplanetary.video/?v=aHR0cHM6Ly9ha2FtYWktY2RuLWNvbnRlbnQuaW50ZXJwbGFuZXRhcnkudmlkZW8vZW1iZWQtMHMwbGZvcmUzb2lpLmh0bWw=",
                "https://akamai.interplanetary.video/?v=aHR0cHM6Ly91cWxvYWQuY29tL2VtYmVkLTRrbnVnNnFtY3BvMS5odG1s"
            ]
        }
    ],
    "downloads": [
        {
            "url": "https://1fichier.com/?21qn8at2zz3wc69q2op7",
            "type": "es"
        }
    ]
}