{
    "url": "https://cuevana.pizza/pelicula/a-happening-of-monumental-proportions",
    "title": "A Happening of Monumental Proportions",
    "duration": "1h 21m",
    "year": "2017",
    "genres": [
        "Comedia"
    ],
    "actors": [
        "Common",
        "Bradley Whitford",
        "Allison Janney",
        "Anders Holm",
        "Rob Riggle",
        "Katie Holmes",
        "Nat Faxon",
        "Jennifer Garner",
        "Marcus Eckert",
        "Storm Reid",
        "John Cho",
        "Kumail Nanjiani",
        "Mary Birdsong",
        "Monica Young",
        "Marla Sokoloff",
        "Lola Glaudini",
        "Al Madrigal",
        "Fran Kranz",
        "Keanu Reeves",
        "Lily Mae Silverstein"
    ],
    "description": "Durante el transcurso de un día, un grupo de estudiantes en una escuela en Los Ángeles se encuentran atrapados en una trama de sexo, mentiras y cadáveres.",
    "cover": "https://cuevana.pizza/resize/###/storage/27589/0HOCbLkVpdOUbSWglB2SoJHd0iOjd7yGNBqMA4D8.jpg",
    "players": [
        {
            "type": "sub",
            "urls": [
                "https://akamai.interplanetary.video/?v=aHR0cHM6Ly9ha2FtYWktY2RuLWNvbnRlbnQuaW50ZXJwbGFuZXRhcnkudmlkZW8vZW1iZWQta3A4N2ZreTV0MXhwLmh0bWw=",
                "https://akamai.interplanetary.video/?v=aHR0cHM6Ly91cWxvYWQuY29tL2VtYmVkLXdxdGtjNXVweDBoNi5odG1s"
            ]
        }
    ],
    "downloads": [
        {
            "url": "https://1fichier.com/?wtp0u8fpskmcfrhk5dbz",
            "type": "en"
        }
    ]
}