{
    "url": "https://cuevana.pizza/pelicula/megan-leavey",
    "title": "Megan Leavey",
    "duration": "1h 56m",
    "year": "2017",
    "genres": [
        "Drama",
        "Guerra",
        "Biografia"
    ],
    "actors": [
        "Kate Mara",
        "Ramón Rodríguez",
        "Tom Felton",
        "Bradley Whitford",
        "Will Patton",
        "Sam Keeley",
        "Common",
        "Edie Falco",
        "Damson Idris",
        "Shannon Tarbet",
        "Alex Hafner",
        "Parker Sawyers",
        "Corey Weaver",
        "Geraldine James",
        "Corey Johnson",
        "Miguel Gomez",
        "Catherine Dyer",
        "Melina Matthews",
        "Jonathan Howard",
        "Mish Boyko"
    ],
    "description": "Historia sobre la soldado de marines Megan Leavy y su perro militar, que estuvieron en la guerra de Iraq y sufrieron una violenta explosión.",
    "cover": "https://cuevana.pizza/resize/###/storage/25650/BjOxfDtFsZWnEmuLgxDhotLgMoKnEEHL4StXvlwv.jpg",
    "players": [
        {
            "type": "lat",
            "urls": [
                "https://akamai.interplanetary.video/?v=aHR0cHM6Ly9ha2FtYWktY2RuLWNvbnRlbnQuaW50ZXJwbGFuZXRhcnkudmlkZW8vZW1iZWQtazZpZ2QweW1kdHpxLmh0bWw=",
                "https://akamai.interplanetary.video/?v=aHR0cHM6Ly91cWxvYWQuY29tL2VtYmVkLWpnNWZhMzloazdqeS5odG1s"
            ]
        },
        {
            "type": "cas",
            "urls": [
                "https://akamai.interplanetary.video/?v=aHR0cHM6Ly9ha2FtYWktY2RuLWNvbnRlbnQuaW50ZXJwbGFuZXRhcnkudmlkZW8vZW1iZWQtcWRwcmZ0Ym13NmtlLmh0bWw=",
                "https://akamai.interplanetary.video/?v=aHR0cHM6Ly91cWxvYWQuY29tL2VtYmVkLWduMXU5ZXpmdzVmMi5odG1s"
            ]
        },
        {
            "type": "sub",
            "urls": [
                "https://akamai.interplanetary.video/?v=aHR0cHM6Ly9ha2FtYWktY2RuLWNvbnRlbnQuaW50ZXJwbGFuZXRhcnkudmlkZW8vZW1iZWQtbXZ0MzNzc2MxdWk0Lmh0bWw=",
                "https://akamai.interplanetary.video/?v=aHR0cHM6Ly91cWxvYWQuY29tL2VtYmVkLWFpaXUwNTN4NWRubi5odG1s"
            ]
        }
    ],
    "downloads": [
        {
            "url": "https://1fichier.com/?98d86yc7drvq3f1ct6h3",
            "type": "la"
        },
        {
            "url": "https://1fichier.com/?dtklf49ecr2bfty7jb5r",
            "type": "es"
        },
        {
            "url": "https://1fichier.com/?p52zp9lvjc9bb807i9u0",
            "type": "en"
        }
    ]
}