{
    "url": "https://cuevana.pizza/pelicula/120-pulsaciones-por-minuto",
    "title": "120 pulsaciones por minuto",
    "duration": "2h 22m",
    "year": "2017",
    "genres": [
        "Drama"
    ],
    "actors": [
        "Nahuel Pérez Biscayart",
        "Arnaud Valois",
        "Adèle Haenel",
        "Antoine Reinartz",
        "Félix Maritaud",
        "Ariel Borenstein",
        "Aloïse Sauvage",
        "Simon Bourgade",
        "Mehdi Touré",
        "Simon Guélat",
        "Coralie Russier",
        "Catherine Vinatier",
        "Théophile Ray",
        "Saadia Bentaïeb",
        "Jean-François Auguste",
        "Julien Herbin",
        "Samuel Churin",
        "Rahim-Silvioli Mehdi",
        "Pascal Tantot",
        "Yves Heck"
    ],
    "description": "París, principios de los años 90. Un grupo de jóvenes activistas intenta generar conciencia sobre el SIDA. Un nuevo miembro del grupo, Nathan, se quedará sorprendido ante la radicalidad y energía de Sean, que gasta su último aliento en la lucha.",
    "cover": "https://cuevana.pizza/resize/###/storage/25337/uMdawLHIxW4RG6B48s7HqPa792UH4B0iP78wMYsk.jpg",
    "players": [
        {
            "type": "cas",
            "urls": [
                "https://akamai.interplanetary.video/?v=aHR0cHM6Ly9ha2FtYWktY2RuLWNvbnRlbnQuaW50ZXJwbGFuZXRhcnkudmlkZW8vZW1iZWQtaXFzajZobzF3b3YwLmh0bWw=",
                "https://akamai.interplanetary.video/?v=aHR0cHM6Ly91cWxvYWQuY29tL2VtYmVkLTA1cXNoaTRnZzI2dS5odG1s"
            ]
        },
        {
            "type": "sub",
            "urls": [
                "https://akamai.interplanetary.video/?v=aHR0cHM6Ly9ha2FtYWktY2RuLWNvbnRlbnQuaW50ZXJwbGFuZXRhcnkudmlkZW8vZW1iZWQtYjYyenFlejJ6eTViLmh0bWw=",
                "https://akamai.interplanetary.video/?v=aHR0cHM6Ly91cWxvYWQuY29tL2VtYmVkLWoxNTFvbWd0Nm44YS5odG1s"
            ]
        }
    ],
    "downloads": [
        {
            "url": "https://1fichier.com/?lr80nf9xfjxqt2vcimr5",
            "type": "es"
        },
        {
            "url": "https://1fichier.com/?zdy91u6hlkb3llkuxsg6",
            "type": "en"
        }
    ]
}