{
    "url": "https://cuevana.pizza/pelicula/los-limites-del-control",
    "title": "Los límites del control",
    "duration": "1h 56m",
    "year": "2009",
    "genres": [
        "Drama",
        "Misterio",
        "Suspenso",
        "Crimen"
    ],
    "actors": [
        "Isaach De Bankolé",
        "Tilda Swinton",
        "Bill Murray",
        "Gael García Bernal",
        "John Hurt",
        "Youki Kudoh",
        "Paz de la Huerta",
        "Alex Descas",
        "Jean-François Stévenin",
        "Óscar Jaenada",
        "Hiam Abbass",
        "Luis Tosar",
        "Héctor Colomé",
        "María Isasi",
        "Norma Yessenia Paladines"
    ],
    "description": "Un hombre misterioso, desconfiado y solitario (Isaach De Bankolé) que vive al margen de la ley y lleva siempre un violín bajo el brazo, llega a España con la intención de terminar un trabajo. En su camino se cruzarán los más peculiares personajes.",
    "cover": "https://cuevana.pizza/resize/###/storage/29216/sc3VX1aW6LrYcoBvfX7DyjSoSOoraF4AFSqoDfcG.jpg",
    "players": [],
    "downloads": []
}