{
    "url": "https://cuevana.pizza/pelicula/rapidos-y-furiosos-3-desafio-tokyo",
    "title": "Rápidos y furiosos 3: Desafío Tokyo",
    "duration": "1h 44m",
    "year": "2006",
    "genres": [
        "Accion",
        "Drama",
        "Suspenso",
        "Crimen"
    ],
    "actors": [
        "Damien Marzette",
        "Lucas Black",
        "Trula M. Marcus",
        "Zachery Ty Bryan",
        "Nathalie Kelley",
        "Sung Kang",
        "Shad Moss",
        "Brian Tee",
        "Leonardo Nam",
        "Brian Goodman"
    ],
    "description": "Shaun Boswell es un chico que no acaba de encajar en ningún grupo. Su única conexión con el mundo de indiferencia que le rodea es a través de las carreras ilegales, lo que no le ha convertido en el chico favorito de la policía. Cuando amenazan con encarcelarle, le mandan fuera del país a pasar una temporada con su tío, un militar destinado en Japón. En el país donde nacieron la mayoría de los coches modificados, las simples carreras en la calle principal han sido sustituidas por el último reto automovilístico que desafía la gravedad, las carreras de \"drift\" (arrastre), una peligrosa mezcla de velocidad en pistas con curvas muy cerradas y en zigzag. En su primera incursión en el salvaje mundo de las carreras de \"drift\", Shaun acepta ingenuamente conducir un D.K, el Rey del Drift, que pertenece a los Yakuza, la mafia japonesa. Para pagar su deuda, no tiene más remedio que codearse con el hampa de Tokio y jugarse la vida.",
    "cover": "https://cuevana.pizza/resize/###/storage/4402/xOrbjnvdV5sAruXfW50pDQQAjiendAhmvcuCZCet.jpg",
    "players": [
        {
            "type": "lat",
            "urls": [
                "https://akamai.interplanetary.video/?v=aHR0cHM6Ly9ha2FtYWktY2RuLWNvbnRlbnQuaW50ZXJwbGFuZXRhcnkudmlkZW8vZW1iZWQtMjJ6aGt5cmh4Y3huLmh0bWw=",
                "https://akamai.interplanetary.video/?v=aHR0cHM6Ly91cWxvYWQuY29tL2VtYmVkLTY0Y2Z2bndsdXg0Zi5odG1s"
            ]
        },
        {
            "type": "cas",
            "urls": [
                "https://akamai.interplanetary.video/?v=aHR0cHM6Ly9ha2FtYWktY2RuLWNvbnRlbnQuaW50ZXJwbGFuZXRhcnkudmlkZW8vZW1iZWQtZmZybmxjM2Z0a2hsLmh0bWw=",
                "https://akamai.interplanetary.video/?v=aHR0cHM6Ly91cWxvYWQuY29tL2VtYmVkLXh3MGMwZWdrOXF5bC5odG1s"
            ]
        },
        {
            "type": "sub",
            "urls": [
                "https://akamai.interplanetary.video/?v=aHR0cHM6Ly9ha2FtYWktY2RuLWNvbnRlbnQuaW50ZXJwbGFuZXRhcnkudmlkZW8vZW1iZWQtdmQ0NDN5aHllN3EzLmh0bWw=",
                "https://akamai.interplanetary.video/?v=aHR0cHM6Ly91cWxvYWQuY29tL2VtYmVkLW5xb3R3aGRmdXpjdC5odG1s"
            ]
        }
    ],
    "downloads": [
        {
            "url": "https://1fichier.com/?b0gkh6gofu",
            "type": "la"
        },
        {
            "url": "https://1fichier.com/?m12akt9p0e0p4n34wcps",
            "type": "es"
        },
        {
            "url": "https://1fichier.com/?56krl5b6vjvk8l70iakb",
            "type": "en"
        }
    ]
}